[{"id":11471937,"url":"https://patchwork.kernel.org/api/covers/11471937/?format=json","web_url":"https://patchwork.kernel.org/cover/11471937/","project":{"id":8,"url":"https://patchwork.kernel.org/api/projects/8/?format=json","name":"KVM development","link_name":"kvm","list_id":"kvm.vger.kernel.org","list_email":"kvm@vger.kernel.org","web_url":"","scm_url":"","webscm_url":""},"msgid":"<20200403071326.29932-1-eric.auger@redhat.com>","date":"2020-04-03T07:13:14","name":"[kvm-unit-tests,v4,00/12] KVM: arm64: PMUv3 Event Counter Tests","submitter":{"id":168665,"url":"https://patchwork.kernel.org/api/people/168665/?format=json","name":"Auger Eric","email":"eric.auger@redhat.com"},"mbox":"https://patchwork.kernel.org/cover/11471937/mbox/","series":[{"id":265761,"url":"https://patchwork.kernel.org/api/series/265761/?format=json","web_url":"https://patchwork.kernel.org/project/kvm/list/?series=265761","date":"2020-04-03T07:13:14","name":"KVM: arm64: PMUv3 Event Counter Tests","version":4,"mbox":"https://patchwork.kernel.org/series/265761/mbox/"}],"comments":"https://patchwork.kernel.org/api/covers/11471937/comments/"}]